<annotation>
	<folder></folder>
	<filename>RMD02EC198304089_jpg.rf.9b467dfd0c3537ff32c3b2169b3ad6ef.jpg</filename>
	<path>RMD02EC198304089_jpg.rf.9b467dfd0c3537ff32c3b2169b3ad6ef.jpg</path>
	<source>
		<database>roboflow.com</database>
	</source>
	<size>
		<width>480</width>
		<height>640</height>
		<depth>3</depth>
	</size>
	<segmented>0</segmented>
	<object>
		<name>non-helm</name>
		<pose>Unspecified</pose>
		<truncated>0</truncated>
		<difficult>0</difficult>
		<occluded>0</occluded>
		<bndbox>
			<xmin>143</xmin>
			<xmax>162</xmax>
			<ymin>196</ymin>
			<ymax>222</ymax>
		</bndbox>
	</object>
	<object>
		<name>motor</name>
		<pose>Unspecified</pose>
		<truncated>0</truncated>
		<difficult>0</difficult>
		<occluded>0</occluded>
		<bndbox>
			<xmin>85</xmin>
			<xmax>192</xmax>
			<ymin>230</ymin>
			<ymax>365</ymax>
		</bndbox>
	</object>
	<object>
		<name>motor</name>
		<pose>Unspecified</pose>
		<truncated>0</truncated>
		<difficult>0</difficult>
		<occluded>0</occluded>
		<bndbox>
			<xmin>192</xmin>
			<xmax>313</xmax>
			<ymin>250</ymin>
			<ymax>446</ymax>
		</bndbox>
	</object>
	<object>
		<name>non-helm</name>
		<pose>Unspecified</pose>
		<truncated>0</truncated>
		<difficult>0</difficult>
		<occluded>0</occluded>
		<bndbox>
			<xmin>239</xmin>
			<xmax>267</xmax>
			<ymin>201</ymin>
			<ymax>232</ymax>
		</bndbox>
	</object>
	<metadata>
		<tags>
			<tag>motor</tag>
			<tag>non-helm</tag>
		</tags>
	</metadata>
</annotation>
