<annotation>
	<folder></folder>
	<filename>Screenshot-280-_png.rf.824036267af83a23b1cc65e848ab34aa.jpg</filename>
	<path>Screenshot-280-_png.rf.824036267af83a23b1cc65e848ab34aa.jpg</path>
	<source>
		<database>roboflow.com</database>
	</source>
	<size>
		<width>640</width>
		<height>360</height>
		<depth>3</depth>
	</size>
	<segmented>0</segmented>
	<object>
		<name>motor</name>
		<pose>Unspecified</pose>
		<truncated>0</truncated>
		<difficult>0</difficult>
		<occluded>0</occluded>
		<bndbox>
			<xmin>207</xmin>
			<xmax>396</xmax>
			<ymin>164</ymin>
			<ymax>308</ymax>
		</bndbox>
	</object>
	<object>
		<name>non-helm</name>
		<pose>Unspecified</pose>
		<truncated>0</truncated>
		<difficult>0</difficult>
		<occluded>0</occluded>
		<bndbox>
			<xmin>255</xmin>
			<xmax>288</xmax>
			<ymin>135</ymin>
			<ymax>166</ymax>
		</bndbox>
	</object>
	<metadata>
		<tags>
			<tag>motor</tag>
			<tag>non-helm</tag>
		</tags>
	</metadata>
</annotation>
